CHANGELOG.md
LICENSE.md
MANIFEST.in
README.md
setup.cfg
setup.py
django_splitdate/__init__.py
django_splitdate/app_settings.py
django_splitdate/forms.py
django_splitdate.egg-info/PKG-INFO
django_splitdate.egg-info/SOURCES.txt
django_splitdate.egg-info/dependency_links.txt
django_splitdate.egg-info/requires.txt
django_splitdate.egg-info/top_level.txt
django_splitdate/locale/de/LC_MESSAGES/django.mo
django_splitdate/locale/de/LC_MESSAGES/django.po
django_splitdate/locale/en/LC_MESSAGES/django.mo
django_splitdate/locale/en/LC_MESSAGES/django.po