Metadata-Version: 1.1
Name: django-splitdate
Version: 0.1.8
Summary: A widget for django form date fields that displays three inputs (day, month, year).
Home-page: http://github.com/NB-Dev/django-splitdate
Author: Nothrbridge Development Konrad & Schneider GbR
Author-email: mail@nb-dev.de
License: MIT License
Platform: UNKNOWN
Classifier: Environment :: Web Environment
Classifier: Framework :: Django
Classifier: Intended Audience :: Developers
Classifier: License :: OSI Approved :: MIT License
Classifier: Operating System :: OS Independent
Classifier: Programming Language :: Python
Classifier: Programming Language :: Python :: 2
Classifier: Programming Language :: Python :: 2.7
Classifier: Topic :: Internet :: WWW/HTTP
Classifier: Topic :: Internet :: WWW/HTTP :: Dynamic Content
